emptoring
