Metadata-Version: 1.0
Name: emptoring
Version: 0.1.6
Summary: Generic backend http client library
Home-page: https://github.com/SmithSamuelM/emptor
Author: Samuel M Smith
Author-email: smith.samuel.m@gmail.com
License: MIT
Keywords: http client requests
Platform: UNKNOWN
